[
    { "name": "Alice Martin", "level": 1 },
    { "name": "Bob Dupont", "level": 1 },
    { "name": "Charlie Bernard", "level": 1 },
    { "name": "David Morel", "level": 1 },
    { "name": "Emma Lambert", "level": 1 },
    { "name": "Fanny Lefevre", "level": 1 },
    { "name": "Gilles Simon", "level": 1 },
    { "name": "Hugo Caron", "level": 1 },
    { "name": "Inès Petit", "level": 1 },
    { "name": "Jules Robert", "level": 1 },
    { "name": "Karine Leroy", "level": 1 },
    { "name": "Lucien Gautier", "level": 1 },
    { "name": "Manon Fontaine", "level": 1 },
    { "name": "Nicolas Lefebvre", "level": 1 },
    { "name": "Olivier Renault", "level": 1 },
    { "name": "Pauline Simon", "level": 1 },
    { "name": "Quentin Dubois", "level": 1 },
    { "name": "Romain Marchand", "level": 1 },
    { "name": "Sophie Blanchard", "level": 1 },
    { "name": "Théo Garnier", "level": 1 },
    { "name": "Ursula Perrot", "level": 1 },
    
    { "name": "Vincent Moreau", "level": 2 },
    { "name": "William Faure", "level": 2 },
    { "name": "Xavier Roche", "level": 2 },
    { "name": "Yasmine Leroy", "level": 2 },
    { "name": "Zacharie Colin", "level": 2 },
    { "name": "Amélie Durand", "level": 2 },
    { "name": "Benoît Lemoine", "level": 2 },
    { "name": "Céline Pichon", "level": 2 },
    { "name": "Dorian Vidal", "level": 2 },
    { "name": "Élodie Girard", "level": 2 },
    { "name": "Florian Charlier", "level": 2 },
    
    { "name": "Gabrielle Roux", "level": 3 },
    { "name": "Hugo Pelletier", "level": 3 },
    { "name": "Isabelle Roussel", "level": 3 },
    { "name": "Jonathan Lefebvre", "level": 3 },
    { "name": "Kévin Dumont", "level": 3 },
    { "name": "Laetitia Renault", "level": 3 },
    { "name": "Matthieu Lambert", "level": 3 },
    { "name": "Noémie Lefranc", "level": 3 },
    { "name": "Olivier Durand", "level": 3 },
  
    { "name": "Pascal Fontaine", "level": 4 },
    { "name": "Quentin Lefèvre", "level": 4 },
    { "name": "Raphaëlle Girard", "level": 4 },
    { "name": "Stéphane Châtelain", "level": 4 },
    { "name": "Thomas Bernard", "level": 4 }
  ]
  